LICENSE
README.md
setup.py
xingyun/__init__.py
xingyun.egg-info/PKG-INFO
xingyun.egg-info/SOURCES.txt
xingyun.egg-info/dependency_links.txt
xingyun.egg-info/requires.txt
xingyun.egg-info/top_level.txt
xingyun/argparser/__init__.py
xingyun/argparser/argparser.py
xingyun/argparser/mydict.py
xingyun/argparser/mynamespace.py
xingyun/cloud/__init__.py
xingyun/cloud/awss3.py
xingyun/cloud/base.py
xingyun/cloud/dropbox.py
xingyun/cloud/egorov_awss3.py
xingyun/cloud/egorov_dropbox.py
xingyun/logger/__init__.py
xingyun/logger/base.py
xingyun/logger/getid.py
xingyun/logger/globaldata.py
xingyun/logger/logger.py
xingyun/random/__init__.py
xingyun/random/fix_random.py
xingyun/random/my_random.py
xingyun/random/set_random_seed.py
xingyun/savecode/__init__.py
xingyun/savecode/get_code.py
xingyun/time/__init__.py
xingyun/time/my_clock.py
xingyun/time/timer.py
xingyun/universal/__init__.py
xingyun/universal/convert.py
xingyun/universal/get_subdict.py
xingyun/universal/import_module.py