Metadata-Version: 2.1
Name: xingyun
Version: 0.0.8.post15
Home-page: http://github.com/FFTYYY/XingYun
Author: Yongyi Yang
Author-email: yongyi@umich.edu
License: MIT
Requires-Python: >=3.10
License-File: LICENSE
Requires-Dist: prettytable>=3.9.0
Requires-Dist: blosc
Requires-Dist: egorovsystem
Requires-Dist: uniittest
Requires-Dist: pdoc3
Requires-Dist: dropbox
